{"24": [{"image_id": "24", "image_url": "24.png", "n_objects": "7", "n_colors": "5", "total_area_px": "212317", "avg_area_px": "30331.0", "min_area": "7825", "max_area": "57600", "min_radius": "50", "max_radius": "120"}, {"objects": [{"object_id": "0", "rr": "625", "cc": "93", "color": "green", "shape": "circle", "radius": "50", "area": "7825", "size": "small", "prob": "1.0", "thresh_dist": "0.6973", "k": "0.3027", "vagueness": "same"}, {"object_id": "1", "rr": "282", "cc": "142", "color": "red", "shape": "circle", "radius": "60", "area": "11277", "size": "small", "prob": "1.0", "thresh_dist": "0.628", "k": "0.3027", "vagueness": "same"}, {"object_id": "2", "rr": "417", "cc": "885", "color": "yellow", "shape": "circle", "radius": "120", "area": "45213", "size": "big", "prob": "0.7039", "thresh_dist": "0.0538", "k": "0.3027", "vagueness": "same"}, {"object_id": "3", "rr": "853", "cc": "406", "color": "white", "shape": "square", "radius": "120", "area": "57600", "size": "big", "prob": "0.9987", "thresh_dist": "0.3027", "k": "0.3027", "vagueness": "same"}, {"object_id": "4", "rr": "198", "cc": "563", "color": "blue", "shape": "triangle", "radius": "80", "area": "25602", "size": "small", "prob": "0.9996", "thresh_dist": "0.3402", "k": "0.3027", "vagueness": "same"}, {"object_id": "5", "rr": "352.0", "cc": "435", "color": "white", "shape": "rectangle", "radius": "90", "area": "32400", "size": "small", "prob": "0.9787", "thresh_dist": "0.2036", "k": "0.3027", "vagueness": "same"}, {"object_id": "6", "rr": "640.0", "cc": "536", "color": "red", "shape": "rectangle", "radius": "90", "area": "32400", "size": "small", "prob": "0.9787", "thresh_dist": "0.2036", "k": "0.3027", "vagueness": "same"}]}, {"captions": [{"referent": "0", "caption_true": "Pick the small circle", "prob_RH_R_true": "1.0", "dist_from_thresh:": "0.6973", "k": "0.3027", "vagueness": "same"}]}, {"captions": [{"referent": "0", "caption_true": "Pick the small circle", "prob_RH_R_true": "1.0", "dist_from_thresh:": "0.628", "k": "0.3027", "vagueness": "same"}]}, {"captions": [{"referent": "0", "caption_true": "Pick the small circle", "prob_RH_R_true": "0.9787", "dist_from_thresh:": "0.2036", "k": "0.3027", "vagueness": "same"}]}, {"captions": [{"referent": "0", "caption_true": "Pick the small circle", "prob_RH_R_true": "0.9787", "dist_from_thresh:": "0.2036", "k": "0.3027", "vagueness": "same"}]}, {"captions": [{"referent": "0", "caption_true": "Pick the small circle", "prob_RH_R_true": "0.9996", "dist_from_thresh:": "0.3402", "k": "0.3027", "vagueness": "same"}]}]}