{"62": [{"image_id": "62", "image_url": "62.png", "n_objects": "7", "n_colors": "3", "total_area_px": "179808", "avg_area_px": "25686.8571", "min_area": "3602", "max_area": "57602", "min_radius": "30", "max_radius": "120"}, {"objects": [{"object_id": "0", "rr": "188", "cc": "281", "color": "yellow", "shape": "triangle", "radius": "30", "area": "3602", "size": "small", "prob": "1.0", "thresh_dist": "0.6709", "k": "0.3291", "vagueness": "same"}, {"object_id": "1", "rr": "771", "cc": "271", "color": "green", "shape": "triangle", "radius": "50", "area": "10002", "size": "small", "prob": "1.0", "thresh_dist": "0.5524", "k": "0.3291", "vagueness": "same"}, {"object_id": "2", "rr": "895", "cc": "774", "color": "green", "shape": "triangle", "radius": "120", "area": "57602", "size": "big", "prob": "0.9998", "thresh_dist": "0.3291", "k": "0.3291", "vagueness": "same"}, {"object_id": "3", "rr": "196", "cc": "673", "color": "yellow", "shape": "circle", "radius": "110", "area": "37969", "size": "small", "prob": "0.6451", "thresh_dist": "0.0344", "k": "0.3291", "vagueness": "same"}, {"object_id": "4", "rr": "390", "cc": "258", "color": "white", "shape": "square", "radius": "80", "area": "25600", "size": "small", "prob": "0.9978", "thresh_dist": "0.2635", "k": "0.3291", "vagueness": "same"}, {"object_id": "5", "rr": "441", "cc": "517", "color": "yellow", "shape": "circle", "radius": "90", "area": "25433", "size": "small", "prob": "0.998", "thresh_dist": "0.2666", "k": "0.3291", "vagueness": "same"}, {"object_id": "6", "rr": "598.0", "cc": "828", "color": "green", "shape": "rectangle", "radius": "70", "area": "19600", "size": "small", "prob": "1.0", "thresh_dist": "0.3746", "k": "0.3291", "vagueness": "same"}]}, {"captions": [{"referent": "0", "caption_true": "Pick the small triangle", "prob_RH_R_true": "1.0", "dist_from_thresh:": "0.3746", "k": "0.3291", "vagueness": "same"}]}, {"captions": [{"referent": "0", "caption_true": "Pick the small triangle", "prob_RH_R_true": "0.9978", "dist_from_thresh:": "0.2635", "k": "0.3291", "vagueness": "same"}]}]}