{"40": [{"image_id": "40", "image_url": "40.png", "n_objects": "7", "n_colors": "3", "total_area_px": "91516", "avg_area_px": "13073.7143", "min_area": "5013", "max_area": "25433", "min_radius": "40", "max_radius": "90"}, {"objects": [{"object_id": "0", "rr": "340", "cc": "823", "color": "green", "shape": "circle", "radius": "90", "area": "25433", "size": "big", "prob": "0.8436", "thresh_dist": "0.2472", "k": "0.2472", "vagueness": "same"}, {"object_id": "1", "rr": "167", "cc": "423", "color": "green", "shape": "circle", "radius": "80", "area": "20069", "size": "small", "prob": "0.5253", "thresh_dist": "0.0155", "k": "0.2472", "vagueness": "different"}, {"object_id": "2", "rr": "334", "cc": "113", "color": "yellow", "shape": "circle", "radius": "40", "area": "5013", "size": "small", "prob": "0.9989", "thresh_dist": "0.7528", "k": "0.2472", "vagueness": "same"}, {"object_id": "3", "rr": "539", "cc": "794", "color": "white", "shape": "triangle", "radius": "50", "area": "10201", "size": "small", "prob": "0.9792", "thresh_dist": "0.4988", "k": "0.2472", "vagueness": "same"}, {"object_id": "4", "rr": "444", "cc": "495", "color": "white", "shape": "square", "radius": "50", "area": "10000", "size": "small", "prob": "0.9811", "thresh_dist": "0.5086", "k": "0.2472", "vagueness": "same"}, {"object_id": "5", "rr": "682", "cc": "612.0", "color": "white", "shape": "rectangle", "radius": "60", "area": "14400", "size": "small", "prob": "0.8844", "thresh_dist": "0.2931", "k": "0.2472", "vagueness": "same"}, {"object_id": "6", "rr": "499.0", "cc": "362", "color": "white", "shape": "rectangle", "radius": "40", "area": "6400", "size": "small", "prob": "0.9974", "thresh_dist": "0.6849", "k": "0.2472", "vagueness": "same"}]}, {"captions": [{"referent": "0", "caption_true": "Pick the big circle", "prob_RH_R_true": "0.9811", "dist_from_thresh:": "0.5086", "k": "0.2472", "vagueness": "same"}]}, {"captions": [{"referent": "0", "caption_true": "Pick the big circle", "prob_RH_R_true": "0.9792", "dist_from_thresh:": "0.4988", "k": "0.2472", "vagueness": "same"}]}, {"captions": [{"referent": "0", "caption_true": "Pick the big circle", "prob_RH_R_true": "0.9989", "dist_from_thresh:": "0.7528", "k": "0.2472", "vagueness": "same"}]}]}